aloe/__init__.py
aloe/cache.py
aloe/cli.py
aloe/files.py
aloe/partial.py
aloe/plotter.py
aloe/test/__init__.py
aloe/test/test_cache.py
aloe/test/test_files.py
aloe/test/test_plotter.py
aloe_pattern-0.5.dist-info/DESCRIPTION.rst
aloe_pattern-0.5.dist-info/METADATA
aloe_pattern-0.5.dist-info/RECORD
aloe_pattern-0.5.dist-info/WHEEL
aloe_pattern-0.5.dist-info/entry_points.txt
aloe_pattern-0.5.dist-info/metadata.json
aloe_pattern-0.5.dist-info/top_level.txt
